django_bower_cache-0.5.0.dist-info/RECORD
django_bower_cache-0.5.0.dist-info/DESCRIPTION.rst
django_bower_cache-0.5.0.dist-info/metadata.json
django_bower_cache-0.5.0.dist-info/WHEEL
django_bower_cache-0.5.0.dist-info/METADATA
django_bower_cache-0.5.0.dist-info/top_level.txt
registry/query.py
registry/views.py
registry/bowerlib.py
registry/_compat.py
registry/managers.py
registry/serializers.py
registry/models.py
registry/admin.py
registry/gitwrapper.py
registry/tasks.py
registry/__init__.py
registry/templates/500.html
registry/templates/404.html
registry/templates/admin/registry/clonedrepo/change_list.html
registry/templates/admin/registry/clonedrepo/change_form.html
registry/templates/admin/registry/clonedrepo/add_model_fieldset.html
