Metadata-Version: 2.0
Name: django-bower-cache
Version: 0.5.0
Summary: A Django app implementing a local caching proxy for Bower packages.
Home-page: https://github.com/tinche/django-bower-cache
Author: Tin Tvrtkovic
Author-email: tinchester@gmail.com
License: MIT
Keywords: bower
Platform: UNKNOWN
Classifier: Development Status :: 3 - Alpha
Classifier: Framework :: Django
Classifier: Intended Audience :: System Administrators
Classifier: License :: OSI Approved :: MIT License
Classifier: Natural Language :: English
Classifier: Programming Language :: Python :: 2
Classifier: Programming Language :: Python :: 2.6
Classifier: Programming Language :: Python :: 2.7
Classifier: Programming Language :: Python :: 3.3
Classifier: Programming Language :: Python :: 3.4
Classifier: Programming Language :: Python :: Implementation :: PyPy
Requires-Dist: Django (>=1.6,<1.7)
Requires-Dist: djangorestframework (>=2.3.12,<3.0)
Requires-Dist: envoy (>=0.0.3)
Requires-Dist: requests (>=2.6.0,<2.7.0)
Requires-Dist: celery (>=3.1.11,<3.2)
Requires-Dist: configparser (==3.5.0b2); python_version == "2.6" or python_version == "2.7"
